pelipy/__init__.py
pelipy/objects.py
pelipy/pelican.py
pelipy/permissions.py
pelipy/utils.py
pelipy-1.0.0.dist-info/METADATA
pelipy-1.0.0.dist-info/WHEEL
pelipy-1.0.0.dist-info/top_level.txt
pelipy-1.0.0.dist-info/RECORD
